gif_for_cli/__init__.py
gif_for_cli/__main__.py
gif_for_cli/constants.py
gif_for_cli/display.py
gif_for_cli/execute.py
gif_for_cli/export.py
gif_for_cli/utils.py
gif_for_cli/generate/__init__.py
gif_for_cli/generate/utils.py
gif_for_cli/generate/x256fgbg_utils.py
gif_for_cli/third_party/__init__.py
gif_for_cli/third_party/Roboto_Mono/LICENSE.txt
gif_for_cli/third_party/Roboto_Mono/RobotoMono-Regular.ttf
gif_for_cli/third_party/__pycache__/__init__.cpython-35.pyc
gif_for_cli-1.1.2.dist-info/METADATA
gif_for_cli-1.1.2.dist-info/RECORD
gif_for_cli-1.1.2.dist-info/WHEEL
gif_for_cli-1.1.2.dist-info/entry_points.txt
gif_for_cli-1.1.2.dist-info/top_level.txt
tests/__init__.py
tests/fixtures.py
tests/test_display.py
tests/test_execute.py
tests/test_export.py
tests/test_main.py
tests/test_utils.py
tests/generate/__init__.py
tests/generate/test.py
tests/generate/test_utils.py
